setup.py
khipu/__init__.py
khipu/version.py
khipu.egg-info/PKG-INFO
khipu.egg-info/SOURCES.txt
khipu.egg-info/dependency_links.txt
khipu.egg-info/requires.txt
khipu.egg-info/top_level.txt