Metadata-Version: 1.1
Name: khipu
Version: 0.0.5
Summary: A client for the khipu API.
Home-page: https://github.com/jrperdomoz/khipu
Author: Jonatan Rodriguez
Author-email: jrperdomoz@gmail.com
License: BSD
Keywords: khipu chile
Platform: UNKNOWN
Classifier: Development Status :: 3 - AlphaProgramming Language :: Python :: 2.7
